README.md
setup.py
TaLiSSman.egg-info/PKG-INFO
TaLiSSman.egg-info/SOURCES.txt
TaLiSSman.egg-info/dependency_links.txt
TaLiSSman.egg-info/requires.txt
TaLiSSman.egg-info/top_level.txt
talissman/__init__.py
talissman/model/__init__.py
talissman/model/padding.py
talissman/model/unet.py
talissman/model/utils.py
talissman/training/__init__.py
talissman/training/callbacks.py
talissman/training/data_augmentation.py
talissman/training/helpers.py
talissman/training/training.py