Metadata-Version: 2.1
Name: TaLiSSman
Version: 0.0.2
Summary: Segmentation of bacteria growing in agar-pads, imaged by transmitted light stacks
Home-page: https://github.com/jeanollion/talissman
Author: Jean Ollion
Author-email: jean.ollion@polytechnique.org
License: UNKNOWN
Download-URL: https://github.com/jeanollion/TaLiSSman/archive/v0.0.1.tar.gz
Keywords: Segmentation,Bacteria,Transmitted Light,Bright Field,Stack,Microscopy
Platform: UNKNOWN
Classifier: Development Status :: 4 - Beta
Classifier: Intended Audience :: Science/Research
Classifier: Topic :: Scientific/Engineering :: Artificial Intelligence
Classifier: Topic :: Scientific/Engineering :: Image Processing
Classifier: License :: OSI Approved :: GNU General Public License v3 or later (GPLv3+)
Classifier: Programming Language :: Python :: 3
Requires-Python: >=3
